[{"Date": 202501, "Account Name": "عمرو المحمدي ", "City": "MONUFIA", "Brick": "MADINT AL-SADAT", "line": "C.V.M 3", "acc_id": "226722", "Division": "CVM 3_MENOFIA II", "District Manager": "Ramy Ahmed Ibrahim Bedewy", "Area Manager": "Other", "pharmacy Name": "['بشير الحداد', 'ص.سمعان القس بطرس']", "Phar.Sales Qnty": 0.0, "Phar.Sales Value": 0.0, "Territory": "MENOFEYA III", "Zone": "Delta"}, {"Date": 202502, "Account Name": "عمرو المحمدي ", "City": "MONUFIA", "Brick": "MADINT AL-SADAT", "line": "C.V.M 3", "acc_id": "226722", "Division": "CVM 3_MENOFIA II", "District Manager": "Ramy Ahmed Ibrahim Bedewy", "Area Manager": "Other", "pharmacy Name": "['بشير الحداد', 'ص.سمعان القس بطرس']", "Phar.Sales Qnty": 6.5, "Phar.Sales Value": 130.585, "Territory": "MENOFEYA III", "Zone": "Delta"}, {"Date": 202503, "Account Name": "عمرو المحمدي ", "City": "MONUFIA", "Brick": "MADINT AL-SADAT", "line": "C.V.M 3", "acc_id": "226722", "Division": "CVM 3_MENOFIA II", "District Manager": "Ramy Ahmed Ibrahim Bedewy", "Area Manager": "Other", "pharmacy Name": "['بشير الحداد', 'ص.سمعان القس بطرس']", "Phar.Sales Qnty": 0.0, "Phar.Sales Value": 0.0, "Territory": "MENOFEYA III", "Zone": "Delta"}, {"Date": 202504, "Account Name": "عمرو المحمدي ", "City": "MONUFIA", "Brick": "MADINT AL-SADAT", "line": "C.V.M 3", "acc_id": "226722", "Division": "CVM 3_MENOFIA II", "District Manager": "Ramy Ahmed Ibrahim Bedewy", "Area Manager": "Other", "pharmacy Name": "['بشير الحداد', 'ص.سمعان القس بطرس']", "Phar.Sales Qnty": 0.0, "Phar.Sales Value": 0.0, "Territory": "MENOFEYA III", "Zone": "Delta"}, {"Date": 202505, "Account Name": "عمرو المحمدي ", "City": "MONUFIA", "Brick": "MADINT AL-SADAT", "line": "C.V.M 3", "acc_id": "226722", "Division": "CVM 3_MENOFIA II", "District Manager": "Ramy Ahmed Ibrahim Bedewy", "Area Manager": "Other", "pharmacy Name": "['بشير الحداد', 'ص.سمعان القس بطرس']", "Phar.Sales Qnty": 0.0, "Phar.Sales Value": 0.0, "Territory": "MENOFEYA III", "Zone": "Delta"}, {"Date": 202506, "Account Name": "عمرو المحمدي ", "City": "MONUFIA", "Brick": "MADINT AL-SADAT", "line": "C.V.M 3", "acc_id": "226722", "Division": "CVM 3_MENOFIA II", "District Manager": "Ramy Ahmed Ibrahim Bedewy", "Area Manager": "Other", "pharmacy Name": "['بشير الحداد', 'ص.سمعان القس بطرس']", "Phar.Sales Qnty": 0.0, "Phar.Sales Value": 0.0, "Territory": "MENOFEYA III", "Zone": "Delta"}, {"Date": 202507, "Account Name": "عمرو المحمدي ", "City": "MONUFIA", "Brick": "MADINT AL-SADAT", "line": "C.V.M 3", "acc_id": "226722", "Division": "CVM 3_MENOFIA II", "District Manager": "Ramy Ahmed Ibrahim Bedewy", "Area Manager": "Other", "pharmacy Name": "['بشير الحداد', 'ص.سمعان القس بطرس']", "Phar.Sales Qnty": 0.0, "Phar.Sales Value": 0.0, "Territory": "MENOFEYA III", "Zone": "Delta"}, {"Date": 202508, "Account Name": "عمرو المحمدي ", "City": "MONUFIA", "Brick": "MADINT AL-SADAT", "line": "C.V.M 3", "acc_id": "226722", "Division": "CVM 3_MENOFIA II", "District Manager": "Ramy Ahmed Ibrahim Bedewy", "Area Manager": "Other", "pharmacy Name": "['بشير الحداد', 'ص.سمعان القس بطرس']", "Phar.Sales Qnty": 0.0, "Phar.Sales Value": 0.0, "Territory": "MENOFEYA III", "Zone": "Delta"}, {"Date": 202509, "Account Name": "عمرو المحمدي ", "City": "MONUFIA", "Brick": "MADINT AL-SADAT", "line": "C.V.M 3", "acc_id": "226722", "Division": "CVM 3_MENOFIA II", "District Manager": "Ramy Ahmed Ibrahim Bedewy", "Area Manager": "Other", "pharmacy Name": "['بشير الحداد', 'ص.سمعان القس بطرس']", "Phar.Sales Qnty": 0.0, "Phar.Sales Value": 0.0, "Territory": "MENOFEYA III", "Zone": "Delta"}]