[{"Date": 202501, "Account Name": "مصطفى عبد الرازق كامل", "City": "MINYA", "Brick": "BANY MAZAR", "line": "['C.V.M 2', 'C.V.M 1']", "acc_id": "108962", "Division": "['SHT_El Menya I', 'C.V.S 2_El Menya I']", "District Manager": "Mina Fahmy Abdo", "Area Manager": "Micheal Nashaat Ragheb Samaan", "pharmacy Name": "['صيدلية ابوخشبه', 'صيدلية الحجاز', 'صيدلية زينب بكرى بكرى']", "Phar.Sales Qnty": 0.0, "Phar.Sales Value": 0.0, "Territory": "EL MENYA I", "Zone": "Upper Egypt"}, {"Date": 202502, "Account Name": "مصطفى عبد الرازق كامل", "City": "MINYA", "Brick": "BANY MAZAR", "line": "['C.V.M 2', 'C.V.M 1']", "acc_id": "108962", "Division": "['SHT_El Menya I', 'C.V.S 2_El Menya I']", "District Manager": "Mina Fahmy Abdo", "Area Manager": "Micheal Nashaat Ragheb Samaan", "pharmacy Name": "['صيدلية ابوخشبه', 'صيدلية الحجاز', 'صيدلية زينب بكرى بكرى']", "Phar.Sales Qnty": 0.0, "Phar.Sales Value": 0.0, "Territory": "EL MENYA I", "Zone": "Upper Egypt"}, {"Date": 202503, "Account Name": "مصطفى عبد الرازق كامل", "City": "MINYA", "Brick": "BANY MAZAR", "line": "['C.V.M 2', 'C.V.M 1']", "acc_id": "108962", "Division": "['SHT_El Menya I', 'C.V.S 2_El Menya I']", "District Manager": "Mina Fahmy Abdo", "Area Manager": "Micheal Nashaat Ragheb Samaan", "pharmacy Name": "['صيدلية ابوخشبه', 'صيدلية الحجاز', 'صيدلية زينب بكرى بكرى']", "Phar.Sales Qnty": 0.0, "Phar.Sales Value": 0.0, "Territory": "EL MENYA I", "Zone": "Upper Egypt"}, {"Date": 202504, "Account Name": "مصطفى عبد الرازق كامل", "City": "MINYA", "Brick": "BANY MAZAR", "line": "['C.V.M 2', 'C.V.M 1']", "acc_id": "108962", "Division": "['SHT_El Menya I', 'C.V.S 2_El Menya I']", "District Manager": "Mina Fahmy Abdo", "Area Manager": "Micheal Nashaat Ragheb Samaan", "pharmacy Name": "['صيدلية ابوخشبه', 'صيدلية الحجاز', 'صيدلية زينب بكرى بكرى']", "Phar.Sales Qnty": 0.0, "Phar.Sales Value": 0.0, "Territory": "EL MENYA I", "Zone": "Upper Egypt"}, {"Date": 202505, "Account Name": "مصطفى عبد الرازق كامل", "City": "MINYA", "Brick": "BANY MAZAR", "line": "['C.V.M 2', 'C.V.M 1']", "acc_id": "108962", "Division": "['SHT_El Menya I', 'C.V.S 2_El Menya I']", "District Manager": "Mina Fahmy Abdo", "Area Manager": "Micheal Nashaat Ragheb Samaan", "pharmacy Name": "['صيدلية ابوخشبه', 'صيدلية الحجاز', 'صيدلية زينب بكرى بكرى']", "Phar.Sales Qnty": 5.0, "Phar.Sales Value": 739.7736938, "Territory": "EL MENYA I", "Zone": "Upper Egypt"}, {"Date": 202506, "Account Name": "مصطفى عبد الرازق كامل", "City": "MINYA", "Brick": "BANY MAZAR", "line": "['C.V.M 2', 'C.V.M 1']", "acc_id": "108962", "Division": "['SHT_El Menya I', 'C.V.S 2_El Menya I']", "District Manager": "Mina Fahmy Abdo", "Area Manager": "Micheal Nashaat Ragheb Samaan", "pharmacy Name": "['صيدلية ابوخشبه', 'صيدلية الحجاز', 'صيدلية زينب بكرى بكرى']", "Phar.Sales Qnty": 0.0, "Phar.Sales Value": 0.0, "Territory": "EL MENYA I", "Zone": "Upper Egypt"}, {"Date": 202507, "Account Name": "مصطفى عبد الرازق كامل", "City": "MINYA", "Brick": "BANY MAZAR", "line": "['C.V.M 2', 'C.V.M 1']", "acc_id": "108962", "Division": "['SHT_El Menya I', 'C.V.S 2_El Menya I']", "District Manager": "Mina Fahmy Abdo", "Area Manager": "Micheal Nashaat Ragheb Samaan", "pharmacy Name": "['صيدلية ابوخشبه', 'صيدلية الحجاز', 'صيدلية زينب بكرى بكرى']", "Phar.Sales Qnty": 2.5, "Phar.Sales Value": 50.225, "Territory": "EL MENYA I", "Zone": "Upper Egypt"}, {"Date": 202508, "Account Name": "مصطفى عبد الرازق كامل", "City": "MINYA", "Brick": "BANY MAZAR", "line": "['C.V.M 2', 'C.V.M 1']", "acc_id": "108962", "Division": "['SHT_El Menya I', 'C.V.S 2_El Menya I']", "District Manager": "Mina Fahmy Abdo", "Area Manager": "Micheal Nashaat Ragheb Samaan", "pharmacy Name": "['صيدلية ابوخشبه', 'صيدلية الحجاز', 'صيدلية زينب بكرى بكرى']", "Phar.Sales Qnty": 3.0, "Phar.Sales Value": 516.99375, "Territory": "EL MENYA I", "Zone": "Upper Egypt"}, {"Date": 202509, "Account Name": "مصطفى عبد الرازق كامل", "City": "MINYA", "Brick": "BANY MAZAR", "line": "['C.V.M 2', 'C.V.M 1']", "acc_id": "108962", "Division": "['SHT_El Menya I', 'C.V.S 2_El Menya I']", "District Manager": "Mina Fahmy Abdo", "Area Manager": "Micheal Nashaat Ragheb Samaan", "pharmacy Name": "['صيدلية ابوخشبه', 'صيدلية الحجاز', 'صيدلية زينب بكرى بكرى']", "Phar.Sales Qnty": 0.0, "Phar.Sales Value": 0.0, "Territory": "EL MENYA I", "Zone": "Upper Egypt"}]