[{"Date": 202501, "Account Name": "احمد عبدالراضى", "City": "QENA & Red", "Brick": "QENA", "line": "['C.V.M 2', 'C.V.M 5']", "acc_id": "93197", "Division": "['C.V.M 5_Up III_Sohag', 'C.V.S 2_QUENA I/RED SEA']", "District Manager": "['Kerolos Nady Michael Mina', 'Mina Mahfouz Metry']", "Area Manager": "['Micheal Nashaat Ragheb Samaan', 'Other']", "pharmacy Name": "['صيدلية احمد عبدالفتاح النقيب', 'صيدلية النحاس الجديده', 'صيدلية رقية احمد فايز قاسم']", "Phar.Sales Qnty": 8.0, "Phar.Sales Value": 2061.5301, "Territory": "QUENA I - RED SEA", "Zone": "Upper Egypt"}, {"Date": 202502, "Account Name": "احمد عبدالراضى", "City": "QENA & Red", "Brick": "QENA", "line": "['C.V.M 2', 'C.V.M 5']", "acc_id": "93197", "Division": "['C.V.M 5_Up III_Sohag', 'C.V.S 2_QUENA I/RED SEA']", "District Manager": "['Kerolos Nady Michael Mina', 'Mina Mahfouz Metry']", "Area Manager": "['Micheal Nashaat Ragheb Samaan', 'Other']", "pharmacy Name": "['صيدلية احمد عبدالفتاح النقيب', 'صيدلية النحاس الجديده', 'صيدلية رقية احمد فايز قاسم']", "Phar.Sales Qnty": 18.75, "Phar.Sales Value": 3159.8049, "Territory": "QUENA I - RED SEA", "Zone": "Upper Egypt"}, {"Date": 202503, "Account Name": "احمد عبدالراضى", "City": "QENA & Red", "Brick": "QENA", "line": "['C.V.M 2', 'C.V.M 5']", "acc_id": "93197", "Division": "['C.V.M 5_Up III_Sohag', 'C.V.S 2_QUENA I/RED SEA']", "District Manager": "['Kerolos Nady Michael Mina', 'Mina Mahfouz Metry']", "Area Manager": "['Micheal Nashaat Ragheb Samaan', 'Other']", "pharmacy Name": "['صيدلية احمد عبدالفتاح النقيب', 'صيدلية النحاس الجديده', 'صيدلية رقية احمد فايز قاسم']", "Phar.Sales Qnty": 14.0, "Phar.Sales Value": 332.0315, "Territory": "QUENA I - RED SEA", "Zone": "Upper Egypt"}, {"Date": 202504, "Account Name": "احمد عبدالراضى", "City": "QENA & Red", "Brick": "QENA", "line": "['C.V.M 2', 'C.V.M 5']", "acc_id": "93197", "Division": "['C.V.M 5_Up III_Sohag', 'C.V.S 2_QUENA I/RED SEA']", "District Manager": "['Kerolos Nady Michael Mina', 'Mina Mahfouz Metry']", "Area Manager": "['Micheal Nashaat Ragheb Samaan', 'Other']", "pharmacy Name": "['صيدلية احمد عبدالفتاح النقيب', 'صيدلية النحاس الجديده', 'صيدلية رقية احمد فايز قاسم']", "Phar.Sales Qnty": 4.0, "Phar.Sales Value": 766.521, "Territory": "QUENA I - RED SEA", "Zone": "Upper Egypt"}, {"Date": 202505, "Account Name": "احمد عبدالراضى", "City": "QENA & Red", "Brick": "QENA", "line": "['C.V.M 2', 'C.V.M 5']", "acc_id": "93197", "Division": "['C.V.M 5_Up III_Sohag', 'C.V.S 2_QUENA I/RED SEA']", "District Manager": "['Kerolos Nady Michael Mina', 'Mina Mahfouz Metry']", "Area Manager": "['Micheal Nashaat Ragheb Samaan', 'Other']", "pharmacy Name": "['صيدلية احمد عبدالفتاح النقيب', 'صيدلية النحاس الجديده', 'صيدلية رقية احمد فايز قاسم']", "Phar.Sales Qnty": 2.0, "Phar.Sales Value": 370.51201, "Territory": "QUENA I - RED SEA", "Zone": "Upper Egypt"}, {"Date": 202506, "Account Name": "احمد عبدالراضى", "City": "QENA & Red", "Brick": "QENA", "line": "['C.V.M 2', 'C.V.M 5']", "acc_id": "93197", "Division": "['C.V.M 5_Up III_Sohag', 'C.V.S 2_QUENA I/RED SEA']", "District Manager": "['Kerolos Nady Michael Mina', 'Mina Mahfouz Metry']", "Area Manager": "['Micheal Nashaat Ragheb Samaan', 'Other']", "pharmacy Name": "['صيدلية احمد عبدالفتاح النقيب', 'صيدلية النحاس الجديده', 'صيدلية رقية احمد فايز قاسم']", "Phar.Sales Qnty": 4.5, "Phar.Sales Value": 219.857, "Territory": "QUENA I - RED SEA", "Zone": "Upper Egypt"}, {"Date": 202507, "Account Name": "احمد عبدالراضى", "City": "QENA & Red", "Brick": "QENA", "line": "['C.V.M 2', 'C.V.M 5']", "acc_id": "93197", "Division": "['C.V.M 5_Up III_Sohag', 'C.V.S 2_QUENA I/RED SEA']", "District Manager": "['Kerolos Nady Michael Mina', 'Mina Mahfouz Metry']", "Area Manager": "['Micheal Nashaat Ragheb Samaan', 'Other']", "pharmacy Name": "['صيدلية احمد عبدالفتاح النقيب', 'صيدلية النحاس الجديده', 'صيدلية رقية احمد فايز قاسم']", "Phar.Sales Qnty": 7.75, "Phar.Sales Value": 2362.6429, "Territory": "QUENA I - RED SEA", "Zone": "Upper Egypt"}, {"Date": 202508, "Account Name": "احمد عبدالراضى", "City": "QENA & Red", "Brick": "QENA", "line": "['C.V.M 2', 'C.V.M 5']", "acc_id": "93197", "Division": "['C.V.M 5_Up III_Sohag', 'C.V.S 2_QUENA I/RED SEA']", "District Manager": "['Kerolos Nady Michael Mina', 'Mina Mahfouz Metry']", "Area Manager": "['Micheal Nashaat Ragheb Samaan', 'Other']", "pharmacy Name": "['صيدلية احمد عبدالفتاح النقيب', 'صيدلية النحاس الجديده', 'صيدلية رقية احمد فايز قاسم']", "Phar.Sales Qnty": 6.333333333000001, "Phar.Sales Value": 358.608, "Territory": "QUENA I - RED SEA", "Zone": "Upper Egypt"}, {"Date": 202509, "Account Name": "احمد عبدالراضى", "City": "QENA & Red", "Brick": "QENA", "line": "['C.V.M 2', 'C.V.M 5']", "acc_id": "93197", "Division": "['C.V.M 5_Up III_Sohag', 'C.V.S 2_QUENA I/RED SEA']", "District Manager": "['Kerolos Nady Michael Mina', 'Mina Mahfouz Metry']", "Area Manager": "['Micheal Nashaat Ragheb Samaan', 'Other']", "pharmacy Name": "['صيدلية احمد عبدالفتاح النقيب', 'صيدلية النحاس الجديده', 'صيدلية رقية احمد فايز قاسم']", "Phar.Sales Qnty": 7.733333333, "Phar.Sales Value": 529.505, "Territory": "QUENA I - RED SEA", "Zone": "Upper Egypt"}]