[{"Date": 202501, "Account Name": "مؤنس سالم", "City": "BENI SUEF", "Brick": "AL-WASTA CITY", "line": "C.V.M 2", "acc_id": "152193", "Division": "C.V.S 2_BANI SUIF", "District Manager": "Mina Fahmy Abdo", "Area Manager": "Micheal Nashaat Ragheb Samaan", "pharmacy Name": "صيدلية احمد عبدالعظيم", "Phar.Sales Qnty": 2.0, "Phar.Sales Value": 156.24, "Territory": "BANI SUEF", "Zone": "Delta"}, {"Date": 202502, "Account Name": "مؤنس سالم", "City": "BENI SUEF", "Brick": "AL-WASTA CITY", "line": "C.V.M 2", "acc_id": "152193", "Division": "C.V.S 2_BANI SUIF", "District Manager": "Mina Fahmy Abdo", "Area Manager": "Micheal Nashaat Ragheb Samaan", "pharmacy Name": "صيدلية احمد عبدالعظيم", "Phar.Sales Qnty": 1.0, "Phar.Sales Value": 93.744, "Territory": "BANI SUEF", "Zone": "Delta"}, {"Date": 202503, "Account Name": "مؤنس سالم", "City": "BENI SUEF", "Brick": "AL-WASTA CITY", "line": "C.V.M 2", "acc_id": "152193", "Division": "C.V.S 2_BANI SUIF", "District Manager": "Mina Fahmy Abdo", "Area Manager": "Micheal Nashaat Ragheb Samaan", "pharmacy Name": "صيدلية احمد عبدالعظيم", "Phar.Sales Qnty": 4.5, "Phar.Sales Value": 580.7935, "Territory": "BANI SUEF", "Zone": "Delta"}, {"Date": 202504, "Account Name": "مؤنس سالم", "City": "BENI SUEF", "Brick": "AL-WASTA CITY", "line": "C.V.M 2", "acc_id": "152193", "Division": "C.V.S 2_BANI SUIF", "District Manager": "Mina Fahmy Abdo", "Area Manager": "Micheal Nashaat Ragheb Samaan", "pharmacy Name": "صيدلية احمد عبدالعظيم", "Phar.Sales Qnty": 1.0, "Phar.Sales Value": 20.09, "Territory": "BANI SUEF", "Zone": "Delta"}, {"Date": 202505, "Account Name": "مؤنس سالم", "City": "BENI SUEF", "Brick": "AL-WASTA CITY", "line": "C.V.M 2", "acc_id": "152193", "Division": "C.V.S 2_BANI SUIF", "District Manager": "Mina Fahmy Abdo", "Area Manager": "Micheal Nashaat Ragheb Samaan", "pharmacy Name": "صيدلية احمد عبدالعظيم", "Phar.Sales Qnty": 0.0, "Phar.Sales Value": 0.0, "Territory": "BANI SUEF", "Zone": "Delta"}, {"Date": 202506, "Account Name": "مؤنس سالم", "City": "BENI SUEF", "Brick": "AL-WASTA CITY", "line": "C.V.M 2", "acc_id": "152193", "Division": "C.V.S 2_BANI SUIF", "District Manager": "Mina Fahmy Abdo", "Area Manager": "Micheal Nashaat Ragheb Samaan", "pharmacy Name": "صيدلية احمد عبدالعظيم", "Phar.Sales Qnty": 0.5, "Phar.Sales Value": 10.045, "Territory": "BANI SUEF", "Zone": "Delta"}, {"Date": 202507, "Account Name": "مؤنس سالم", "City": "BENI SUEF", "Brick": "AL-WASTA CITY", "line": "C.V.M 2", "acc_id": "152193", "Division": "C.V.S 2_BANI SUIF", "District Manager": "Mina Fahmy Abdo", "Area Manager": "Micheal Nashaat Ragheb Samaan", "pharmacy Name": "صيدلية احمد عبدالعظيم", "Phar.Sales Qnty": 0.5, "Phar.Sales Value": 10.045, "Territory": "BANI SUEF", "Zone": "Delta"}, {"Date": 202508, "Account Name": "مؤنس سالم", "City": "BENI SUEF", "Brick": "AL-WASTA CITY", "line": "C.V.M 2", "acc_id": "152193", "Division": "C.V.S 2_BANI SUIF", "District Manager": "Mina Fahmy Abdo", "Area Manager": "Micheal Nashaat Ragheb Samaan", "pharmacy Name": "صيدلية احمد عبدالعظيم", "Phar.Sales Qnty": 0.0, "Phar.Sales Value": 0.0, "Territory": "BANI SUEF", "Zone": "Delta"}, {"Date": 202509, "Account Name": "مؤنس سالم", "City": "BENI SUEF", "Brick": "AL-WASTA CITY", "line": "C.V.M 2", "acc_id": "152193", "Division": "C.V.S 2_BANI SUIF", "District Manager": "Mina Fahmy Abdo", "Area Manager": "Micheal Nashaat Ragheb Samaan", "pharmacy Name": "صيدلية احمد عبدالعظيم", "Phar.Sales Qnty": 0.25, "Phar.Sales Value": 5.0225, "Territory": "BANI SUEF", "Zone": "Delta"}]