[{"Date": 202501, "Account Name": "معتصم غنيم", "City": "DAKAHLIA", "Brick": "AL-MANSOURA (3)", "line": "C.V.M 3", "acc_id": "121633", "Division": "CVM 3_DAKAHLIA I", "District Manager": "Karim Mohamed Ahmed Ali", "Area Manager": "Other", "pharmacy Name": "عبداللطيف الطرشوبى - هشام الطرشوبى", "Phar.Sales Qnty": 0.0, "Phar.Sales Value": 0.0, "Territory": "DAKHLEIAH I", "Zone": "Delta"}, {"Date": 202502, "Account Name": "معتصم غنيم", "City": "DAKAHLIA", "Brick": "AL-MANSOURA (3)", "line": "C.V.M 3", "acc_id": "121633", "Division": "CVM 3_DAKAHLIA I", "District Manager": "Karim Mohamed Ahmed Ali", "Area Manager": "Other", "pharmacy Name": "عبداللطيف الطرشوبى - هشام الطرشوبى", "Phar.Sales Qnty": 90.0, "Phar.Sales Value": 11911.536, "Territory": "DAKHLEIAH I", "Zone": "Delta"}, {"Date": 202503, "Account Name": "معتصم غنيم", "City": "DAKAHLIA", "Brick": "AL-MANSOURA (3)", "line": "C.V.M 3", "acc_id": "121633", "Division": "CVM 3_DAKAHLIA I", "District Manager": "Karim Mohamed Ahmed Ali", "Area Manager": "Other", "pharmacy Name": "عبداللطيف الطرشوبى - هشام الطرشوبى", "Phar.Sales Qnty": 596.0, "Phar.Sales Value": 26925.29, "Territory": "DAKHLEIAH I", "Zone": "Delta"}, {"Date": 202504, "Account Name": "معتصم غنيم", "City": "DAKAHLIA", "Brick": "AL-MANSOURA (3)", "line": "C.V.M 3", "acc_id": "121633", "Division": "CVM 3_DAKAHLIA I", "District Manager": "Karim Mohamed Ahmed Ali", "Area Manager": "Other", "pharmacy Name": "عبداللطيف الطرشوبى - هشام الطرشوبى", "Phar.Sales Qnty": 1125.0, "Phar.Sales Value": 51182.38125, "Territory": "DAKHLEIAH I", "Zone": "Delta"}, {"Date": 202505, "Account Name": "معتصم غنيم", "City": "DAKAHLIA", "Brick": "AL-MANSOURA (3)", "line": "C.V.M 3", "acc_id": "121633", "Division": "CVM 3_DAKAHLIA I", "District Manager": "Karim Mohamed Ahmed Ali", "Area Manager": "Other", "pharmacy Name": "عبداللطيف الطرشوبى - هشام الطرشوبى", "Phar.Sales Qnty": 80.1, "Phar.Sales Value": 14087.136, "Territory": "DAKHLEIAH I", "Zone": "Delta"}, {"Date": 202506, "Account Name": "معتصم غنيم", "City": "DAKAHLIA", "Brick": "AL-MANSOURA (3)", "line": "C.V.M 3", "acc_id": "121633", "Division": "CVM 3_DAKAHLIA I", "District Manager": "Karim Mohamed Ahmed Ali", "Area Manager": "Other", "pharmacy Name": "عبداللطيف الطرشوبى - هشام الطرشوبى", "Phar.Sales Qnty": 90.0, "Phar.Sales Value": 11911.536, "Territory": "DAKHLEIAH I", "Zone": "Delta"}, {"Date": 202507, "Account Name": "معتصم غنيم", "City": "DAKAHLIA", "Brick": "AL-MANSOURA (3)", "line": "C.V.M 3", "acc_id": "121633", "Division": "CVM 3_DAKAHLIA I", "District Manager": "Karim Mohamed Ahmed Ali", "Area Manager": "Other", "pharmacy Name": "عبداللطيف الطرشوبى - هشام الطرشوبى", "Phar.Sales Qnty": 0.0, "Phar.Sales Value": 0.0, "Territory": "DAKHLEIAH I", "Zone": "Delta"}, {"Date": 202508, "Account Name": "معتصم غنيم", "City": "DAKAHLIA", "Brick": "AL-MANSOURA (3)", "line": "C.V.M 3", "acc_id": "121633", "Division": "CVM 3_DAKAHLIA I", "District Manager": "Karim Mohamed Ahmed Ali", "Area Manager": "Other", "pharmacy Name": "عبداللطيف الطرشوبى - هشام الطرشوبى", "Phar.Sales Qnty": 633.3333333, "Phar.Sales Value": 37024.365, "Territory": "DAKHLEIAH I", "Zone": "Delta"}, {"Date": 202509, "Account Name": "معتصم غنيم", "City": "DAKAHLIA", "Brick": "AL-MANSOURA (3)", "line": "C.V.M 3", "acc_id": "121633", "Division": "CVM 3_DAKAHLIA I", "District Manager": "Karim Mohamed Ahmed Ali", "Area Manager": "Other", "pharmacy Name": "عبداللطيف الطرشوبى - هشام الطرشوبى", "Phar.Sales Qnty": 2253.333333, "Phar.Sales Value": 60411.551, "Territory": "DAKHLEIAH I", "Zone": "Delta"}]