[{"Date": 202501, "Account Name": "أحمد سامي زهران", "City": "MONUFIA", "Brick": "AL-BAGOR", "line": "C.V.M 1", "acc_id": "129113", "Division": "SHT_MENOFIA III", "District Manager": "Yohana Nader Nicola Abdelmalik", "Area Manager": "Mohamed Fahmy Abdelqader Mohamed", "pharmacy Name": "['صيدلية الحكمة', 'احمد كمال بكرى عطيه الحديده', 'صيدلية الخولى']", "Phar.Sales Qnty": 2.0, "Phar.Sales Value": 208.32, "Territory": "MENOFEYA III", "Zone": "Delta"}, {"Date": 202502, "Account Name": "أحمد سامي زهران", "City": "MONUFIA", "Brick": "AL-BAGOR", "line": "C.V.M 1", "acc_id": "129113", "Division": "SHT_MENOFIA III", "District Manager": "Yohana Nader Nicola Abdelmalik", "Area Manager": "Mohamed Fahmy Abdelqader Mohamed", "pharmacy Name": "['صيدلية الحكمة', 'احمد كمال بكرى عطيه الحديده', 'صيدلية الخولى']", "Phar.Sales Qnty": 5.0, "Phar.Sales Value": 133.924, "Territory": "MENOFEYA III", "Zone": "Delta"}, {"Date": 202503, "Account Name": "أحمد سامي زهران", "City": "MONUFIA", "Brick": "AL-BAGOR", "line": "C.V.M 1", "acc_id": "129113", "Division": "SHT_MENOFIA III", "District Manager": "Yohana Nader Nicola Abdelmalik", "Area Manager": "Mohamed Fahmy Abdelqader Mohamed", "pharmacy Name": "['صيدلية الحكمة', 'احمد كمال بكرى عطيه الحديده', 'صيدلية الخولى']", "Phar.Sales Qnty": 8.5, "Phar.Sales Value": 422.975, "Territory": "MENOFEYA III", "Zone": "Delta"}, {"Date": 202504, "Account Name": "أحمد سامي زهران", "City": "MONUFIA", "Brick": "AL-BAGOR", "line": "C.V.M 1", "acc_id": "129113", "Division": "SHT_MENOFIA III", "District Manager": "Yohana Nader Nicola Abdelmalik", "Area Manager": "Mohamed Fahmy Abdelqader Mohamed", "pharmacy Name": "['صيدلية الحكمة', 'احمد كمال بكرى عطيه الحديده', 'صيدلية الخولى']", "Phar.Sales Qnty": 5.0, "Phar.Sales Value": 188.976, "Territory": "MENOFEYA III", "Zone": "Delta"}, {"Date": 202505, "Account Name": "أحمد سامي زهران", "City": "MONUFIA", "Brick": "AL-BAGOR", "line": "C.V.M 1", "acc_id": "129113", "Division": "SHT_MENOFIA III", "District Manager": "Yohana Nader Nicola Abdelmalik", "Area Manager": "Mohamed Fahmy Abdelqader Mohamed", "pharmacy Name": "['صيدلية الحكمة', 'احمد كمال بكرى عطيه الحديده', 'صيدلية الخولى']", "Phar.Sales Qnty": 12.25, "Phar.Sales Value": 992.3125, "Territory": "MENOFEYA III", "Zone": "Delta"}, {"Date": 202506, "Account Name": "أحمد سامي زهران", "City": "MONUFIA", "Brick": "AL-BAGOR", "line": "C.V.M 1", "acc_id": "129113", "Division": "SHT_MENOFIA III", "District Manager": "Yohana Nader Nicola Abdelmalik", "Area Manager": "Mohamed Fahmy Abdelqader Mohamed", "pharmacy Name": "['صيدلية الحكمة', 'احمد كمال بكرى عطيه الحديده', 'صيدلية الخولى']", "Phar.Sales Qnty": 3.5, "Phar.Sales Value": 63.617, "Territory": "MENOFEYA III", "Zone": "Delta"}, {"Date": 202507, "Account Name": "أحمد سامي زهران", "City": "MONUFIA", "Brick": "AL-BAGOR", "line": "C.V.M 1", "acc_id": "129113", "Division": "SHT_MENOFIA III", "District Manager": "Yohana Nader Nicola Abdelmalik", "Area Manager": "Mohamed Fahmy Abdelqader Mohamed", "pharmacy Name": "['صيدلية الحكمة', 'احمد كمال بكرى عطيه الحديده', 'صيدلية الخولى']", "Phar.Sales Qnty": 7.25, "Phar.Sales Value": 507.2245, "Territory": "MENOFEYA III", "Zone": "Delta"}, {"Date": 202508, "Account Name": "أحمد سامي زهران", "City": "MONUFIA", "Brick": "AL-BAGOR", "line": "C.V.M 1", "acc_id": "129113", "Division": "SHT_MENOFIA III", "District Manager": "Yohana Nader Nicola Abdelmalik", "Area Manager": "Mohamed Fahmy Abdelqader Mohamed", "pharmacy Name": "['صيدلية الحكمة', 'احمد كمال بكرى عطيه الحديده', 'صيدلية الخولى']", "Phar.Sales Qnty": 9.5, "Phar.Sales Value": 737.681, "Territory": "MENOFEYA III", "Zone": "Delta"}, {"Date": 202509, "Account Name": "أحمد سامي زهران", "City": "MONUFIA", "Brick": "AL-BAGOR", "line": "C.V.M 1", "acc_id": "129113", "Division": "SHT_MENOFIA III", "District Manager": "Yohana Nader Nicola Abdelmalik", "Area Manager": "Mohamed Fahmy Abdelqader Mohamed", "pharmacy Name": "['صيدلية الحكمة', 'احمد كمال بكرى عطيه الحديده', 'صيدلية الخولى']", "Phar.Sales Qnty": 7.0, "Phar.Sales Value": 590.242525, "Territory": "MENOFEYA III", "Zone": "Delta"}]