[{"Date": 202501, "Account Name": "عبور عبد المجيد", "City": "MINYA", "Brick": "DEIR MUASSA", "line": "C.V.M 2", "acc_id": "145677", "Division": "C.V.S 2_El Menya II", "District Manager": "Mina Fahmy Abdo", "Area Manager": "Micheal Nashaat Ragheb Samaan", "pharmacy Name": "['السلام', 'صيدلية احمد سيد عمر', 'اميره محمد احمد']", "Phar.Sales Qnty": 0.0, "Phar.Sales Value": 0.0, "Territory": "EL MENYA II", "Zone": "Upper Egypt"}, {"Date": 202502, "Account Name": "عبور عبد المجيد", "City": "MINYA", "Brick": "DEIR MUASSA", "line": "C.V.M 2", "acc_id": "145677", "Division": "C.V.S 2_El Menya II", "District Manager": "Mina Fahmy Abdo", "Area Manager": "Micheal Nashaat Ragheb Samaan", "pharmacy Name": "['السلام', 'صيدلية احمد سيد عمر', 'اميره محمد احمد']", "Phar.Sales Qnty": 0.5, "Phar.Sales Value": 10.045, "Territory": "EL MENYA II", "Zone": "Upper Egypt"}, {"Date": 202503, "Account Name": "عبور عبد المجيد", "City": "MINYA", "Brick": "DEIR MUASSA", "line": "C.V.M 2", "acc_id": "145677", "Division": "C.V.S 2_El Menya II", "District Manager": "Mina Fahmy Abdo", "Area Manager": "Micheal Nashaat Ragheb Samaan", "pharmacy Name": "['السلام', 'صيدلية احمد سيد عمر', 'اميره محمد احمد']", "Phar.Sales Qnty": 0.0, "Phar.Sales Value": 0.0, "Territory": "EL MENYA II", "Zone": "Upper Egypt"}, {"Date": 202504, "Account Name": "عبور عبد المجيد", "City": "MINYA", "Brick": "DEIR MUASSA", "line": "C.V.M 2", "acc_id": "145677", "Division": "C.V.S 2_El Menya II", "District Manager": "Mina Fahmy Abdo", "Area Manager": "Micheal Nashaat Ragheb Samaan", "pharmacy Name": "['السلام', 'صيدلية احمد سيد عمر', 'اميره محمد احمد']", "Phar.Sales Qnty": 0.0, "Phar.Sales Value": 0.0, "Territory": "EL MENYA II", "Zone": "Upper Egypt"}, {"Date": 202505, "Account Name": "عبور عبد المجيد", "City": "MINYA", "Brick": "DEIR MUASSA", "line": "C.V.M 2", "acc_id": "145677", "Division": "C.V.S 2_El Menya II", "District Manager": "Mina Fahmy Abdo", "Area Manager": "Micheal Nashaat Ragheb Samaan", "pharmacy Name": "['السلام', 'صيدلية احمد سيد عمر', 'اميره محمد احمد']", "Phar.Sales Qnty": 0.0, "Phar.Sales Value": 0.0, "Territory": "EL MENYA II", "Zone": "Upper Egypt"}, {"Date": 202506, "Account Name": "عبور عبد المجيد", "City": "MINYA", "Brick": "DEIR MUASSA", "line": "C.V.M 2", "acc_id": "145677", "Division": "C.V.S 2_El Menya II", "District Manager": "Mina Fahmy Abdo", "Area Manager": "Micheal Nashaat Ragheb Samaan", "pharmacy Name": "['السلام', 'صيدلية احمد سيد عمر', 'اميره محمد احمد']", "Phar.Sales Qnty": 0.0, "Phar.Sales Value": 0.0, "Territory": "EL MENYA II", "Zone": "Upper Egypt"}, {"Date": 202507, "Account Name": "عبور عبد المجيد", "City": "MINYA", "Brick": "DEIR MUASSA", "line": "C.V.M 2", "acc_id": "145677", "Division": "C.V.S 2_El Menya II", "District Manager": "Mina Fahmy Abdo", "Area Manager": "Micheal Nashaat Ragheb Samaan", "pharmacy Name": "['السلام', 'صيدلية احمد سيد عمر', 'اميره محمد احمد']", "Phar.Sales Qnty": 0.0, "Phar.Sales Value": 0.0, "Territory": "EL MENYA II", "Zone": "Upper Egypt"}, {"Date": 202508, "Account Name": "عبور عبد المجيد", "City": "MINYA", "Brick": "DEIR MUASSA", "line": "C.V.M 2", "acc_id": "145677", "Division": "C.V.S 2_El Menya II", "District Manager": "Mina Fahmy Abdo", "Area Manager": "Micheal Nashaat Ragheb Samaan", "pharmacy Name": "['السلام', 'صيدلية احمد سيد عمر', 'اميره محمد احمد']", "Phar.Sales Qnty": 0.0, "Phar.Sales Value": 0.0, "Territory": "EL MENYA II", "Zone": "Upper Egypt"}, {"Date": 202509, "Account Name": "عبور عبد المجيد", "City": "MINYA", "Brick": "DEIR MUASSA", "line": "C.V.M 2", "acc_id": "145677", "Division": "C.V.S 2_El Menya II", "District Manager": "Mina Fahmy Abdo", "Area Manager": "Micheal Nashaat Ragheb Samaan", "pharmacy Name": "['السلام', 'صيدلية احمد سيد عمر', 'اميره محمد احمد']", "Phar.Sales Qnty": 0.0, "Phar.Sales Value": 0.0, "Territory": "EL MENYA II", "Zone": "Upper Egypt"}]