[{"Date": 202501, "Account Name": "طلعت عاشور", "City": "GHARBIA", "Brick": "AL-MEHALLA AL-KOUBRA", "line": "['C.V.M 3', 'C.V.M 4']", "acc_id": "157313", "Division": "['CVM 3_GHARBIA II', 'CVM 4_GHARBIA IV']", "District Manager": "['Mahmoud Hosny Mahmoud Mohamed', 'Ramy Ahmed Ibrahim Bedewy']", "Area Manager": "['Other', 'Tamer Mohamed Morci Abdellah']", "pharmacy Name": "صيدلية ناصر", "Phar.Sales Qnty": 63.0, "Phar.Sales Value": 3973.0725, "Territory": "GHARBEIA II", "Zone": "Delta"}, {"Date": 202502, "Account Name": "طلعت عاشور", "City": "GHARBIA", "Brick": "AL-MEHALLA AL-KOUBRA", "line": "['C.V.M 3', 'C.V.M 4']", "acc_id": "157313", "Division": "['CVM 3_GHARBIA II', 'CVM 4_GHARBIA IV']", "District Manager": "['Mahmoud Hosny Mahmoud Mohamed', 'Ramy Ahmed Ibrahim Bedewy']", "Area Manager": "['Other', 'Tamer Mohamed Morci Abdellah']", "pharmacy Name": "صيدلية ناصر", "Phar.Sales Qnty": 102.0, "Phar.Sales Value": 8716.28815, "Territory": "GHARBEIA II", "Zone": "Delta"}, {"Date": 202503, "Account Name": "طلعت عاشور", "City": "GHARBIA", "Brick": "AL-MEHALLA AL-KOUBRA", "line": "['C.V.M 3', 'C.V.M 4']", "acc_id": "157313", "Division": "['CVM 3_GHARBIA II', 'CVM 4_GHARBIA IV']", "District Manager": "['Mahmoud Hosny Mahmoud Mohamed', 'Ramy Ahmed Ibrahim Bedewy']", "Area Manager": "['Other', 'Tamer Mohamed Morci Abdellah']", "pharmacy Name": "صيدلية ناصر", "Phar.Sales Qnty": 127.5, "Phar.Sales Value": 6911.2915, "Territory": "GHARBEIA II", "Zone": "Delta"}, {"Date": 202504, "Account Name": "طلعت عاشور", "City": "GHARBIA", "Brick": "AL-MEHALLA AL-KOUBRA", "line": "['C.V.M 3', 'C.V.M 4']", "acc_id": "157313", "Division": "['CVM 3_GHARBIA II', 'CVM 4_GHARBIA IV']", "District Manager": "['Mahmoud Hosny Mahmoud Mohamed', 'Ramy Ahmed Ibrahim Bedewy']", "Area Manager": "['Other', 'Tamer Mohamed Morci Abdellah']", "pharmacy Name": "صيدلية ناصر", "Phar.Sales Qnty": 15.0, "Phar.Sales Value": 2581.272, "Territory": "GHARBEIA II", "Zone": "Delta"}, {"Date": 202505, "Account Name": "طلعت عاشور", "City": "GHARBIA", "Brick": "AL-MEHALLA AL-KOUBRA", "line": "['C.V.M 3', 'C.V.M 4']", "acc_id": "157313", "Division": "['CVM 3_GHARBIA II', 'CVM 4_GHARBIA IV']", "District Manager": "['Mahmoud Hosny Mahmoud Mohamed', 'Ramy Ahmed Ibrahim Bedewy']", "Area Manager": "['Other', 'Tamer Mohamed Morci Abdellah']", "pharmacy Name": "صيدلية ناصر", "Phar.Sales Qnty": 20.0, "Phar.Sales Value": 3299.707125, "Territory": "GHARBEIA II", "Zone": "Delta"}, {"Date": 202506, "Account Name": "طلعت عاشور", "City": "GHARBIA", "Brick": "AL-MEHALLA AL-KOUBRA", "line": "['C.V.M 3', 'C.V.M 4']", "acc_id": "157313", "Division": "['CVM 3_GHARBIA II', 'CVM 4_GHARBIA IV']", "District Manager": "['Mahmoud Hosny Mahmoud Mohamed', 'Ramy Ahmed Ibrahim Bedewy']", "Area Manager": "['Other', 'Tamer Mohamed Morci Abdellah']", "pharmacy Name": "صيدلية ناصر", "Phar.Sales Qnty": 30.0, "Phar.Sales Value": 4117.84425, "Territory": "GHARBEIA II", "Zone": "Delta"}, {"Date": 202507, "Account Name": "طلعت عاشور", "City": "GHARBIA", "Brick": "AL-MEHALLA AL-KOUBRA", "line": "['C.V.M 3', 'C.V.M 4']", "acc_id": "157313", "Division": "['CVM 3_GHARBIA II', 'CVM 4_GHARBIA IV']", "District Manager": "['Mahmoud Hosny Mahmoud Mohamed', 'Ramy Ahmed Ibrahim Bedewy']", "Area Manager": "['Other', 'Tamer Mohamed Morci Abdellah']", "pharmacy Name": "صيدلية ناصر", "Phar.Sales Qnty": 22.5, "Phar.Sales Value": 2819.97225, "Territory": "GHARBEIA II", "Zone": "Delta"}, {"Date": 202508, "Account Name": "طلعت عاشور", "City": "GHARBIA", "Brick": "AL-MEHALLA AL-KOUBRA", "line": "['C.V.M 3', 'C.V.M 4']", "acc_id": "157313", "Division": "['CVM 3_GHARBIA II', 'CVM 4_GHARBIA IV']", "District Manager": "['Mahmoud Hosny Mahmoud Mohamed', 'Ramy Ahmed Ibrahim Bedewy']", "Area Manager": "['Other', 'Tamer Mohamed Morci Abdellah']", "pharmacy Name": "صيدلية ناصر", "Phar.Sales Qnty": 131.83333334, "Phar.Sales Value": 11388.21075, "Territory": "GHARBEIA II", "Zone": "Delta"}, {"Date": 202509, "Account Name": "طلعت عاشور", "City": "GHARBIA", "Brick": "AL-MEHALLA AL-KOUBRA", "line": "['C.V.M 3', 'C.V.M 4']", "acc_id": "157313", "Division": "['CVM 3_GHARBIA II', 'CVM 4_GHARBIA IV']", "District Manager": "['Mahmoud Hosny Mahmoud Mohamed', 'Ramy Ahmed Ibrahim Bedewy']", "Area Manager": "['Other', 'Tamer Mohamed Morci Abdellah']", "pharmacy Name": "صيدلية ناصر", "Phar.Sales Qnty": 40.6, "Phar.Sales Value": 4094.198, "Territory": "GHARBEIA II", "Zone": "Delta"}]