[{"Date": 202501, "Account Name": "ايمن رفعت", "City": "BENI SUEF", "Brick": "['BANI SEUIF CITY1', 'BANI SEUIF CITY2']", "line": "['C.V.M 2', 'C.V.M 1']", "acc_id": "151929", "Division": "['SHT_BANI SUIF I', 'C.V.S 2_BANI SUIF']", "District Manager": "Mina Fahmy Abdo", "Area Manager": "Micheal Nashaat Ragheb Samaan", "pharmacy Name": "['صيدلية فريد عكاشة', 'صيدلية صبحي محمد انور', 'صيدلية مني احمد عباس']", "Phar.Sales Qnty": 77.0, "Phar.Sales Value": 7205.4442500000005, "Territory": "BANI SUEF", "Zone": "Delta"}, {"Date": 202502, "Account Name": "ايمن رفعت", "City": "BENI SUEF", "Brick": "['BANI SEUIF CITY1', 'BANI SEUIF CITY2']", "line": "['C.V.M 2', 'C.V.M 1']", "acc_id": "151929", "Division": "['SHT_BANI SUIF I', 'C.V.S 2_BANI SUIF']", "District Manager": "Mina Fahmy Abdo", "Area Manager": "Micheal Nashaat Ragheb Samaan", "pharmacy Name": "['صيدلية فريد عكاشة', 'صيدلية صبحي محمد انور', 'صيدلية مني احمد عباس']", "Phar.Sales Qnty": 196.0, "Phar.Sales Value": 10547.4425, "Territory": "BANI SUEF", "Zone": "Delta"}, {"Date": 202503, "Account Name": "ايمن رفعت", "City": "BENI SUEF", "Brick": "['BANI SEUIF CITY1', 'BANI SEUIF CITY2']", "line": "['C.V.M 2', 'C.V.M 1']", "acc_id": "151929", "Division": "['SHT_BANI SUIF I', 'C.V.S 2_BANI SUIF']", "District Manager": "Mina Fahmy Abdo", "Area Manager": "Micheal Nashaat Ragheb Samaan", "pharmacy Name": "['صيدلية فريد عكاشة', 'صيدلية صبحي محمد انور', 'صيدلية مني احمد عباس']", "Phar.Sales Qnty": 53.0, "Phar.Sales Value": 8880.9531, "Territory": "BANI SUEF", "Zone": "Delta"}, {"Date": 202504, "Account Name": "ايمن رفعت", "City": "BENI SUEF", "Brick": "['BANI SEUIF CITY1', 'BANI SEUIF CITY2']", "line": "['C.V.M 2', 'C.V.M 1']", "acc_id": "151929", "Division": "['SHT_BANI SUIF I', 'C.V.S 2_BANI SUIF']", "District Manager": "Mina Fahmy Abdo", "Area Manager": "Micheal Nashaat Ragheb Samaan", "pharmacy Name": "['صيدلية فريد عكاشة', 'صيدلية صبحي محمد انور', 'صيدلية مني احمد عباس']", "Phar.Sales Qnty": 38.5, "Phar.Sales Value": 4012.86985, "Territory": "BANI SUEF", "Zone": "Delta"}, {"Date": 202505, "Account Name": "ايمن رفعت", "City": "BENI SUEF", "Brick": "['BANI SEUIF CITY1', 'BANI SEUIF CITY2']", "line": "['C.V.M 2', 'C.V.M 1']", "acc_id": "151929", "Division": "['SHT_BANI SUIF I', 'C.V.S 2_BANI SUIF']", "District Manager": "Mina Fahmy Abdo", "Area Manager": "Micheal Nashaat Ragheb Samaan", "pharmacy Name": "['صيدلية فريد عكاشة', 'صيدلية صبحي محمد انور', 'صيدلية مني احمد عباس']", "Phar.Sales Qnty": 50.0, "Phar.Sales Value": 11647.5789, "Territory": "BANI SUEF", "Zone": "Delta"}, {"Date": 202506, "Account Name": "ايمن رفعت", "City": "BENI SUEF", "Brick": "['BANI SEUIF CITY1', 'BANI SEUIF CITY2']", "line": "['C.V.M 2', 'C.V.M 1']", "acc_id": "151929", "Division": "['SHT_BANI SUIF I', 'C.V.S 2_BANI SUIF']", "District Manager": "Mina Fahmy Abdo", "Area Manager": "Micheal Nashaat Ragheb Samaan", "pharmacy Name": "['صيدلية فريد عكاشة', 'صيدلية صبحي محمد انور', 'صيدلية مني احمد عباس']", "Phar.Sales Qnty": 82.5, "Phar.Sales Value": 9404.48675, "Territory": "BANI SUEF", "Zone": "Delta"}, {"Date": 202507, "Account Name": "ايمن رفعت", "City": "BENI SUEF", "Brick": "['BANI SEUIF CITY1', 'BANI SEUIF CITY2']", "line": "['C.V.M 2', 'C.V.M 1']", "acc_id": "151929", "Division": "['SHT_BANI SUIF I', 'C.V.S 2_BANI SUIF']", "District Manager": "Mina Fahmy Abdo", "Area Manager": "Micheal Nashaat Ragheb Samaan", "pharmacy Name": "['صيدلية فريد عكاشة', 'صيدلية صبحي محمد انور', 'صيدلية مني احمد عباس']", "Phar.Sales Qnty": 81.9, "Phar.Sales Value": 7877.939326, "Territory": "BANI SUEF", "Zone": "Delta"}, {"Date": 202508, "Account Name": "ايمن رفعت", "City": "BENI SUEF", "Brick": "['BANI SEUIF CITY1', 'BANI SEUIF CITY2']", "line": "['C.V.M 2', 'C.V.M 1']", "acc_id": "151929", "Division": "['SHT_BANI SUIF I', 'C.V.S 2_BANI SUIF']", "District Manager": "Mina Fahmy Abdo", "Area Manager": "Micheal Nashaat Ragheb Samaan", "pharmacy Name": "['صيدلية فريد عكاشة', 'صيدلية صبحي محمد انور', 'صيدلية مني احمد عباس']", "Phar.Sales Qnty": 108.13333333, "Phar.Sales Value": 11088.84755, "Territory": "BANI SUEF", "Zone": "Delta"}, {"Date": 202509, "Account Name": "ايمن رفعت", "City": "BENI SUEF", "Brick": "['BANI SEUIF CITY1', 'BANI SEUIF CITY2']", "line": "['C.V.M 2', 'C.V.M 1']", "acc_id": "151929", "Division": "['SHT_BANI SUIF I', 'C.V.S 2_BANI SUIF']", "District Manager": "Mina Fahmy Abdo", "Area Manager": "Micheal Nashaat Ragheb Samaan", "pharmacy Name": "['صيدلية فريد عكاشة', 'صيدلية صبحي محمد انور', 'صيدلية مني احمد عباس']", "Phar.Sales Qnty": 32.1, "Phar.Sales Value": 3721.259175, "Territory": "BANI SUEF", "Zone": "Delta"}]