[{"Date": 202501, "Account Name": "محمود فريك", "City": "BEHEIRA", "Brick": "DAMANHOUR", "line": "['C.V.M 3', 'C.V.M 4', 'C.V.M 2', 'C.V.M 5']", "acc_id": "118525", "Division": "['CVM 3_Behera I', 'C.V.S 2_Behera III', 'CVM 4_Behera II', 'C.V.M 5_ Alex Center_Behera']", "District Manager": "['Mina Adly Fawzy Botros', 'Rana Khaled Mahrous Mselhay', 'Taghreed Abdallah Abdel Moghny Mohamed', 'Ahmed Salah Ahmed El Mahalawy']", "Area Manager": "['Other', 'Michael Joseph Sedhom Gerges', 'Tamer Mohamed Morci Abdellah']", "pharmacy Name": "['صيدلية مجدي', 'صيدلية الزهراء', 'صيدلية محمد صبرى دمنهور']", "Phar.Sales Qnty": 32.0, "Phar.Sales Value": 2638.7265, "Territory": "BEHAIRA I", "Zone": "Delta"}, {"Date": 202502, "Account Name": "محمود فريك", "City": "BEHEIRA", "Brick": "DAMANHOUR", "line": "['C.V.M 3', 'C.V.M 4', 'C.V.M 2', 'C.V.M 5']", "acc_id": "118525", "Division": "['CVM 3_Behera I', 'C.V.S 2_Behera III', 'CVM 4_Behera II', 'C.V.M 5_ Alex Center_Behera']", "District Manager": "['Mina Adly Fawzy Botros', 'Rana Khaled Mahrous Mselhay', 'Taghreed Abdallah Abdel Moghny Mohamed', 'Ahmed Salah Ahmed El Mahalawy']", "Area Manager": "['Other', 'Michael Joseph Sedhom Gerges', 'Tamer Mohamed Morci Abdellah']", "pharmacy Name": "['صيدلية مجدي', 'صيدلية الزهراء', 'صيدلية محمد صبرى دمنهور']", "Phar.Sales Qnty": 21.0, "Phar.Sales Value": 1973.23395, "Territory": "BEHAIRA I", "Zone": "Delta"}, {"Date": 202503, "Account Name": "محمود فريك", "City": "BEHEIRA", "Brick": "DAMANHOUR", "line": "['C.V.M 3', 'C.V.M 4', 'C.V.M 2', 'C.V.M 5']", "acc_id": "118525", "Division": "['CVM 3_Behera I', 'C.V.S 2_Behera III', 'CVM 4_Behera II', 'C.V.M 5_ Alex Center_Behera']", "District Manager": "['Mina Adly Fawzy Botros', 'Rana Khaled Mahrous Mselhay', 'Taghreed Abdallah Abdel Moghny Mohamed', 'Ahmed Salah Ahmed El Mahalawy']", "Area Manager": "['Other', 'Michael Joseph Sedhom Gerges', 'Tamer Mohamed Morci Abdellah']", "pharmacy Name": "['صيدلية مجدي', 'صيدلية الزهراء', 'صيدلية محمد صبرى دمنهور']", "Phar.Sales Qnty": 18.75, "Phar.Sales Value": 1411.59795, "Territory": "BEHAIRA I", "Zone": "Delta"}, {"Date": 202504, "Account Name": "محمود فريك", "City": "BEHEIRA", "Brick": "DAMANHOUR", "line": "['C.V.M 3', 'C.V.M 4', 'C.V.M 2', 'C.V.M 5']", "acc_id": "118525", "Division": "['CVM 3_Behera I', 'C.V.S 2_Behera III', 'CVM 4_Behera II', 'C.V.M 5_ Alex Center_Behera']", "District Manager": "['Mina Adly Fawzy Botros', 'Rana Khaled Mahrous Mselhay', 'Taghreed Abdallah Abdel Moghny Mohamed', 'Ahmed Salah Ahmed El Mahalawy']", "Area Manager": "['Other', 'Michael Joseph Sedhom Gerges', 'Tamer Mohamed Morci Abdellah']", "pharmacy Name": "['صيدلية مجدي', 'صيدلية الزهراء', 'صيدلية محمد صبرى دمنهور']", "Phar.Sales Qnty": 4.0, "Phar.Sales Value": 462.3003, "Territory": "BEHAIRA I", "Zone": "Delta"}, {"Date": 202505, "Account Name": "محمود فريك", "City": "BEHEIRA", "Brick": "DAMANHOUR", "line": "['C.V.M 3', 'C.V.M 4', 'C.V.M 2', 'C.V.M 5']", "acc_id": "118525", "Division": "['CVM 3_Behera I', 'C.V.S 2_Behera III', 'CVM 4_Behera II', 'C.V.M 5_ Alex Center_Behera']", "District Manager": "['Mina Adly Fawzy Botros', 'Rana Khaled Mahrous Mselhay', 'Taghreed Abdallah Abdel Moghny Mohamed', 'Ahmed Salah Ahmed El Mahalawy']", "Area Manager": "['Other', 'Michael Joseph Sedhom Gerges', 'Tamer Mohamed Morci Abdellah']", "pharmacy Name": "['صيدلية مجدي', 'صيدلية الزهراء', 'صيدلية محمد صبرى دمنهور']", "Phar.Sales Qnty": 34.25, "Phar.Sales Value": 2961.819225, "Territory": "BEHAIRA I", "Zone": "Delta"}, {"Date": 202506, "Account Name": "محمود فريك", "City": "BEHEIRA", "Brick": "DAMANHOUR", "line": "['C.V.M 3', 'C.V.M 4', 'C.V.M 2', 'C.V.M 5']", "acc_id": "118525", "Division": "['CVM 3_Behera I', 'C.V.S 2_Behera III', 'CVM 4_Behera II', 'C.V.M 5_ Alex Center_Behera']", "District Manager": "['Mina Adly Fawzy Botros', 'Rana Khaled Mahrous Mselhay', 'Taghreed Abdallah Abdel Moghny Mohamed', 'Ahmed Salah Ahmed El Mahalawy']", "Area Manager": "['Other', 'Michael Joseph Sedhom Gerges', 'Tamer Mohamed Morci Abdellah']", "pharmacy Name": "['صيدلية مجدي', 'صيدلية الزهراء', 'صيدلية محمد صبرى دمنهور']", "Phar.Sales Qnty": 9.25, "Phar.Sales Value": 1009.79535, "Territory": "BEHAIRA I", "Zone": "Delta"}, {"Date": 202507, "Account Name": "محمود فريك", "City": "BEHEIRA", "Brick": "DAMANHOUR", "line": "['C.V.M 3', 'C.V.M 4', 'C.V.M 2', 'C.V.M 5']", "acc_id": "118525", "Division": "['CVM 3_Behera I', 'C.V.S 2_Behera III', 'CVM 4_Behera II', 'C.V.M 5_ Alex Center_Behera']", "District Manager": "['Mina Adly Fawzy Botros', 'Rana Khaled Mahrous Mselhay', 'Taghreed Abdallah Abdel Moghny Mohamed', 'Ahmed Salah Ahmed El Mahalawy']", "Area Manager": "['Other', 'Michael Joseph Sedhom Gerges', 'Tamer Mohamed Morci Abdellah']", "pharmacy Name": "['صيدلية مجدي', 'صيدلية الزهراء', 'صيدلية محمد صبرى دمنهور']", "Phar.Sales Qnty": 40.0, "Phar.Sales Value": 4094.283975, "Territory": "BEHAIRA I", "Zone": "Delta"}, {"Date": 202508, "Account Name": "محمود فريك", "City": "BEHEIRA", "Brick": "DAMANHOUR", "line": "['C.V.M 3', 'C.V.M 4', 'C.V.M 2', 'C.V.M 5']", "acc_id": "118525", "Division": "['CVM 3_Behera I', 'C.V.S 2_Behera III', 'CVM 4_Behera II', 'C.V.M 5_ Alex Center_Behera']", "District Manager": "['Mina Adly Fawzy Botros', 'Rana Khaled Mahrous Mselhay', 'Taghreed Abdallah Abdel Moghny Mohamed', 'Ahmed Salah Ahmed El Mahalawy']", "Area Manager": "['Other', 'Michael Joseph Sedhom Gerges', 'Tamer Mohamed Morci Abdellah']", "pharmacy Name": "['صيدلية مجدي', 'صيدلية الزهراء', 'صيدلية محمد صبرى دمنهور']", "Phar.Sales Qnty": 74.499999999, "Phar.Sales Value": 5305.8075, "Territory": "BEHAIRA I", "Zone": "Delta"}, {"Date": 202509, "Account Name": "محمود فريك", "City": "BEHEIRA", "Brick": "DAMANHOUR", "line": "['C.V.M 3', 'C.V.M 4', 'C.V.M 2', 'C.V.M 5']", "acc_id": "118525", "Division": "['CVM 3_Behera I', 'C.V.S 2_Behera III', 'CVM 4_Behera II', 'C.V.M 5_ Alex Center_Behera']", "District Manager": "['Mina Adly Fawzy Botros', 'Rana Khaled Mahrous Mselhay', 'Taghreed Abdallah Abdel Moghny Mohamed', 'Ahmed Salah Ahmed El Mahalawy']", "Area Manager": "['Other', 'Michael Joseph Sedhom Gerges', 'Tamer Mohamed Morci Abdellah']", "pharmacy Name": "['صيدلية مجدي', 'صيدلية الزهراء', 'صيدلية محمد صبرى دمنهور']", "Phar.Sales Qnty": 62.500000001, "Phar.Sales Value": 4779.5826, "Territory": "BEHAIRA I", "Zone": "Delta"}]