[{"Date": 202501, "Account Name": "محمد خلف", "City": "SOHAG", "Brick": "DAR EL-SALAM", "line": "['C.V.M 3', 'C.V.M 2', 'C.V.M 1']", "acc_id": "101658", "Division": "['SHT_Sohag II', 'EXC_Sohag II', 'C.V.S 2_Sohag I']", "District Manager": "['Mina Mahfouz Metry', 'Sameh Zaref Habib Mekhael']", "Area Manager": "['Micheal Nashaat Ragheb Samaan', 'Other']", "pharmacy Name": "['صيدلية غادة الجديدة-دار السلام-ن', 'صيدلية العوضي', 'احمد العوضى']", "Phar.Sales Qnty": 13.0, "Phar.Sales Value": 1989.06225, "Territory": "SOHAG II", "Zone": "Upper Egypt"}, {"Date": 202502, "Account Name": "محمد خلف", "City": "SOHAG", "Brick": "DAR EL-SALAM", "line": "['C.V.M 3', 'C.V.M 2', 'C.V.M 1']", "acc_id": "101658", "Division": "['SHT_Sohag II', 'EXC_Sohag II', 'C.V.S 2_Sohag I']", "District Manager": "['Mina Mahfouz Metry', 'Sameh Zaref Habib Mekhael']", "Area Manager": "['Micheal Nashaat Ragheb Samaan', 'Other']", "pharmacy Name": "['صيدلية غادة الجديدة-دار السلام-ن', 'صيدلية العوضي', 'احمد العوضى']", "Phar.Sales Qnty": 7.5, "Phar.Sales Value": 150.675, "Territory": "SOHAG II", "Zone": "Upper Egypt"}, {"Date": 202503, "Account Name": "محمد خلف", "City": "SOHAG", "Brick": "DAR EL-SALAM", "line": "['C.V.M 3', 'C.V.M 2', 'C.V.M 1']", "acc_id": "101658", "Division": "['SHT_Sohag II', 'EXC_Sohag II', 'C.V.S 2_Sohag I']", "District Manager": "['Mina Mahfouz Metry', 'Sameh Zaref Habib Mekhael']", "Area Manager": "['Micheal Nashaat Ragheb Samaan', 'Other']", "pharmacy Name": "['صيدلية غادة الجديدة-دار السلام-ن', 'صيدلية العوضي', 'احمد العوضى']", "Phar.Sales Qnty": 3.0, "Phar.Sales Value": 187.488, "Territory": "SOHAG II", "Zone": "Upper Egypt"}, {"Date": 202504, "Account Name": "محمد خلف", "City": "SOHAG", "Brick": "DAR EL-SALAM", "line": "['C.V.M 3', 'C.V.M 2', 'C.V.M 1']", "acc_id": "101658", "Division": "['SHT_Sohag II', 'EXC_Sohag II', 'C.V.S 2_Sohag I']", "District Manager": "['Mina Mahfouz Metry', 'Sameh Zaref Habib Mekhael']", "Area Manager": "['Micheal Nashaat Ragheb Samaan', 'Other']", "pharmacy Name": "['صيدلية غادة الجديدة-دار السلام-ن', 'صيدلية العوضي', 'احمد العوضى']", "Phar.Sales Qnty": 26.25, "Phar.Sales Value": 1495.44, "Territory": "SOHAG II", "Zone": "Upper Egypt"}, {"Date": 202505, "Account Name": "محمد خلف", "City": "SOHAG", "Brick": "DAR EL-SALAM", "line": "['C.V.M 3', 'C.V.M 2', 'C.V.M 1']", "acc_id": "101658", "Division": "['SHT_Sohag II', 'EXC_Sohag II', 'C.V.S 2_Sohag I']", "District Manager": "['Mina Mahfouz Metry', 'Sameh Zaref Habib Mekhael']", "Area Manager": "['Micheal Nashaat Ragheb Samaan', 'Other']", "pharmacy Name": "['صيدلية غادة الجديدة-دار السلام-ن', 'صيدلية العوضي', 'احمد العوضى']", "Phar.Sales Qnty": 5.0, "Phar.Sales Value": 100.44, "Territory": "SOHAG II", "Zone": "Upper Egypt"}, {"Date": 202506, "Account Name": "محمد خلف", "City": "SOHAG", "Brick": "DAR EL-SALAM", "line": "['C.V.M 3', 'C.V.M 2', 'C.V.M 1']", "acc_id": "101658", "Division": "['SHT_Sohag II', 'EXC_Sohag II', 'C.V.S 2_Sohag I']", "District Manager": "['Mina Mahfouz Metry', 'Sameh Zaref Habib Mekhael']", "Area Manager": "['Micheal Nashaat Ragheb Samaan', 'Other']", "pharmacy Name": "['صيدلية غادة الجديدة-دار السلام-ن', 'صيدلية العوضي', 'احمد العوضى']", "Phar.Sales Qnty": 0.0, "Phar.Sales Value": 0.0, "Territory": "SOHAG II", "Zone": "Upper Egypt"}, {"Date": 202507, "Account Name": "محمد خلف", "City": "SOHAG", "Brick": "DAR EL-SALAM", "line": "['C.V.M 3', 'C.V.M 2', 'C.V.M 1']", "acc_id": "101658", "Division": "['SHT_Sohag II', 'EXC_Sohag II', 'C.V.S 2_Sohag I']", "District Manager": "['Mina Mahfouz Metry', 'Sameh Zaref Habib Mekhael']", "Area Manager": "['Micheal Nashaat Ragheb Samaan', 'Other']", "pharmacy Name": "['صيدلية غادة الجديدة-دار السلام-ن', 'صيدلية العوضي', 'احمد العوضى']", "Phar.Sales Qnty": 21.0, "Phar.Sales Value": 2524.05, "Territory": "SOHAG II", "Zone": "Upper Egypt"}, {"Date": 202508, "Account Name": "محمد خلف", "City": "SOHAG", "Brick": "DAR EL-SALAM", "line": "['C.V.M 3', 'C.V.M 2', 'C.V.M 1']", "acc_id": "101658", "Division": "['SHT_Sohag II', 'EXC_Sohag II', 'C.V.S 2_Sohag I']", "District Manager": "['Mina Mahfouz Metry', 'Sameh Zaref Habib Mekhael']", "Area Manager": "['Micheal Nashaat Ragheb Samaan', 'Other']", "pharmacy Name": "['صيدلية غادة الجديدة-دار السلام-ن', 'صيدلية العوضي', 'احمد العوضى']", "Phar.Sales Qnty": 10.166666667, "Phar.Sales Value": 213.171, "Territory": "SOHAG II", "Zone": "Upper Egypt"}, {"Date": 202509, "Account Name": "محمد خلف", "City": "SOHAG", "Brick": "DAR EL-SALAM", "line": "['C.V.M 3', 'C.V.M 2', 'C.V.M 1']", "acc_id": "101658", "Division": "['SHT_Sohag II', 'EXC_Sohag II', 'C.V.S 2_Sohag I']", "District Manager": "['Mina Mahfouz Metry', 'Sameh Zaref Habib Mekhael']", "Area Manager": "['Micheal Nashaat Ragheb Samaan', 'Other']", "pharmacy Name": "['صيدلية غادة الجديدة-دار السلام-ن', 'صيدلية العوضي', 'احمد العوضى']", "Phar.Sales Qnty": 0.0, "Phar.Sales Value": 0.0, "Territory": "SOHAG II", "Zone": "Upper Egypt"}]